{
  "version": 2,
  "name": "haccp-business-manager-staging",
  "buildCommand": "npm run build:staging",
  "devCommand": "npm run dev",
  "installCommand": "npm install",
  "outputDirectory": "docs",
  "routes": [
    {
      "src": "/api/(.*)",
      "dest": "/api/$1"
    },
    {
      "src": "/(.*)",
      "dest": "/index.html"
    }
  ],
  "headers": [
    {
      "source": "/sw.js",
      "headers": [
        {
          "key": "Cache-Control",
          "value": "no-cache, no-store, must-revalidate"
        }
      ]
    },
    {
      "source": "/asset/(.*)",
      "headers": [
        {
          "key": "Cache-Control",
          "value": "public, max-age=86400"
        }
      ]
    }
  ],
  "env": {
    "VITE_APP_ENV": "staging",
    "VITE_DEBUG_MODE": "true",
    "VITE_PWA_ENABLED": "true"
  }
}